skibidi/__init__.py
skibidi-0.0.1.dist-info/METADATA
skibidi-0.0.1.dist-info/WHEEL
skibidi-0.0.1.dist-info/top_level.txt
skibidi-0.0.1.dist-info/RECORD
