Metadata-Version: 2.1
Name: skibidi
Version: 0.0.1
Summary: skibidi
Author: arpy8
Classifier: Programming Language :: Python :: 3
Classifier: License :: OSI Approved :: MIT License
Classifier: Operating System :: OS Independent
